{
    "att_dispatch_client_can_send_now": "0x0000586d", 
    "att_dispatch_client_request_can_send_now_event": "0x00005873", 
    "att_dispatch_register_client": "0x00005879", 
    "att_dispatch_register_server": "0x0000588d", 
    "att_dispatch_server_can_send_now": "0x000058a1", 
    "att_dispatch_server_request_can_send_now_event": "0x000058a7", 
    "att_emit_general_event": "0x00005959", 
    "att_server_can_send_packet_now": "0x00006085", 
    "att_server_deferred_read_response": "0x00006089", 
    "att_server_get_mtu": "0x000060a1", 
    "att_server_indicate": "0x0000610d", 
    "att_server_init": "0x00006191", 
    "att_server_notify": "0x000061cd", 
    "att_server_register_packet_handler": "0x000062e5", 
    "att_server_request_can_send_now_event": "0x000062f1", 
    "att_set_db": "0x0000630d", 
    "att_set_read_callback": "0x00006321", 
    "att_set_write_callback": "0x0000632d", 
    "bd_addr_cmp": "0x0000649d", 
    "bd_addr_copy": "0x000064a3", 
    "bd_addr_to_str": "0x000064ad", 
    "big_endian_read_16": "0x000064e5", 
    "big_endian_read_32": "0x000064ed", 
    "big_endian_store_16": "0x00006501", 
    "big_endian_store_32": "0x0000650d", 
    "btstack_config": "0x00006661", 
    "btstack_memory_pool_create": "0x0000679f", 
    "btstack_memory_pool_free": "0x000067c9", 
    "btstack_memory_pool_get": "0x00006829", 
    "btstack_push_user_msg": "0x00006891", 
    "btstack_push_user_runnable": "0x0000689d", 
    "btstack_reset": "0x000068a9", 
    "char_for_nibble": "0x00006b85", 
    "eTaskConfirmSleepModeStatus": "0x00006e65", 
    "gap_add_dev_to_periodic_list": "0x000074d1", 
    "gap_add_whitelist": "0x000074e1", 
    "gap_aes_encrypt": "0x000074ed", 
    "gap_clear_white_lists": "0x00007525", 
    "gap_clr_adv_set": "0x00007531", 
    "gap_clr_periodic_adv_list": "0x0000753d", 
    "gap_create_connection_cancel": "0x00007549", 
    "gap_default_periodic_adv_sync_transfer_param": "0x00007555", 
    "gap_disconnect": "0x0000756d", 
    "gap_disconnect_all": "0x00007599", 
    "gap_ext_create_connection": "0x000075d9", 
    "gap_get_connection_parameter_range": "0x000076b1", 
    "gap_le_read_channel_map": "0x000076e9", 
    "gap_periodic_adv_create_sync": "0x00007755", 
    "gap_periodic_adv_create_sync_cancel": "0x00007779", 
    "gap_periodic_adv_set_info_transfer": "0x00007785", 
    "gap_periodic_adv_sync_transfer": "0x00007795", 
    "gap_periodic_adv_sync_transfer_param": "0x000077a5", 
    "gap_periodic_adv_term_sync": "0x000077c1", 
    "gap_read_antenna_info": "0x00007849", 
    "gap_read_periodic_adv_list_size": "0x00007855", 
    "gap_read_phy": "0x00007861", 
    "gap_read_remote_used_features": "0x0000786d", 
    "gap_read_remote_version": "0x00007879", 
    "gap_read_rssi": "0x00007885", 
    "gap_remove_whitelist": "0x00007891", 
    "gap_rmv_adv_set": "0x0000790d", 
    "gap_rmv_dev_from_periodic_list": "0x00007919", 
    "gap_rx_test_v2": "0x00007929", 
    "gap_rx_test_v3": "0x00007939", 
    "gap_set_adv_set_random_addr": "0x00007985", 
    "gap_set_callback_for_next_hci": "0x000079c1", 
    "gap_set_connection_cte_request_enable": "0x000079e1", 
    "gap_set_connection_cte_response_enable": "0x000079fd", 
    "gap_set_connection_cte_rx_param": "0x00007a0d", 
    "gap_set_connection_cte_tx_param": "0x00007a61", 
    "gap_set_connection_parameter_range": "0x00007aad", 
    "gap_set_connectionless_cte_tx_enable": "0x00007ac5", 
    "gap_set_connectionless_cte_tx_param": "0x00007ad5", 
    "gap_set_connectionless_iq_sampling_enable": "0x00007b31", 
    "gap_set_data_length": "0x00007b8d", 
    "gap_set_def_phy": "0x00007ba5", 
    "gap_set_ext_adv_data": "0x00007bb5", 
    "gap_set_ext_adv_enable": "0x00007bcd", 
    "gap_set_ext_adv_para": "0x00007c3d", 
    "gap_set_ext_scan_enable": "0x00007d15", 
    "gap_set_ext_scan_para": "0x00007d2d", 
    "gap_set_ext_scan_response_data": "0x00007dcd", 
    "gap_set_host_channel_classification": "0x00007de5", 
    "gap_set_periodic_adv_data": "0x00007df5", 
    "gap_set_periodic_adv_enable": "0x00007e65", 
    "gap_set_periodic_adv_para": "0x00007e75", 
    "gap_set_periodic_adv_rx_enable": "0x00007e8d", 
    "gap_set_phy": "0x00007e9d", 
    "gap_set_random_device_address": "0x00007eb9", 
    "gap_start_ccm": "0x00007ee9", 
    "gap_test_end": "0x00007f31", 
    "gap_tx_test_v2": "0x00007f3d", 
    "gap_tx_test_v4": "0x00007f55", 
    "gap_update_connection_parameters": "0x00007f79", 
    "gap_vendor_tx_continuous_wave": "0x00007fb9", 
    "gatt_client_cancel_write": "0x000084e1", 
    "gatt_client_discover_characteristic_descriptors": "0x00008507", 
    "gatt_client_discover_characteristics_for_handle_range_by_uuid128": "0x00008547", 
    "gatt_client_discover_characteristics_for_handle_range_by_uuid16": "0x00008597", 
    "gatt_client_discover_characteristics_for_service": "0x000085e7", 
    "gatt_client_discover_primary_services": "0x0000861d", 
    "gatt_client_discover_primary_services_by_uuid128": "0x0000864f", 
    "gatt_client_discover_primary_services_by_uuid16": "0x00008693", 
    "gatt_client_execute_write": "0x000086cf", 
    "gatt_client_find_included_services_for_service": "0x000086f5", 
    "gatt_client_get_mtu": "0x00008723", 
    "gatt_client_is_ready": "0x000087c1", 
    "gatt_client_listen_for_characteristic_value_updates": "0x000087d7", 
    "gatt_client_prepare_write": "0x000087f7", 
    "gatt_client_read_characteristic_descriptor_using_descriptor_handle": "0x00008833", 
    "gatt_client_read_long_characteristic_descriptor_using_descriptor_handle": "0x0000885d", 
    "gatt_client_read_long_characteristic_descriptor_using_descriptor_handle_with_offset": "0x00008863", 
    "gatt_client_read_long_value_of_characteristic_using_value_handle": "0x00008891", 
    "gatt_client_read_long_value_of_characteristic_using_value_handle_with_offset": "0x00008897", 
    "gatt_client_read_multiple_characteristic_values": "0x000088c5", 
    "gatt_client_read_value_of_characteristic_using_value_handle": "0x000088f5", 
    "gatt_client_read_value_of_characteristics_by_uuid128": "0x00008923", 
    "gatt_client_read_value_of_characteristics_by_uuid16": "0x0000896f", 
    "gatt_client_register_handler": "0x000089b9", 
    "gatt_client_reliable_write_long_value_of_characteristic": "0x000089c5", 
    "gatt_client_signed_write_without_response": "0x00008dc9", 
    "gatt_client_write_characteristic_descriptor_using_descriptor_handle": "0x00008e8d", 
    "gatt_client_write_client_characteristic_configuration": "0x00008ec7", 
    "gatt_client_write_long_characteristic_descriptor_using_descriptor_handle": "0x00008f19", 
    "gatt_client_write_long_characteristic_descriptor_using_descriptor_handle_with_offset": "0x00008f29", 
    "gatt_client_write_long_value_of_characteristic": "0x00008f65", 
    "gatt_client_write_long_value_of_characteristic_with_offset": "0x00008f75", 
    "gatt_client_write_value_of_characteristic": "0x00008fb1", 
    "gatt_client_write_value_of_characteristic_without_response": "0x00008fe7", 
    "hci_add_event_handler": "0x0000a51d", 
    "hci_power_control": "0x0000aca5", 
    "hci_register_acl_packet_handler": "0x0000ae59", 
    "kv_commit": "0x0000b5c1", 
    "kv_get": "0x0000b61d", 
    "kv_init": "0x0000b629", 
    "kv_init_backend": "0x0000b6a5", 
    "kv_put": "0x0000b6b9", 
    "kv_remove": "0x0000b6c5", 
    "kv_remove_all": "0x0000b6f9", 
    "kv_value_modified": "0x0000b729", 
    "kv_value_modified_of_key": "0x0000b745", 
    "kv_visit": "0x0000b751", 
    "l2cap_add_event_handler": "0x0000b7e1", 
    "l2cap_can_send_packet_now": "0x0000b7f1", 
    "l2cap_create_le_credit_based_connection_request": "0x0000b9ad", 
    "l2cap_credit_based_send": "0x0000baf1", 
    "l2cap_credit_based_send_continue": "0x0000bb1d", 
    "l2cap_disconnect": "0x0000bb99", 
    "l2cap_get_le_credit_based_connection_credits": "0x0000bde9", 
    "l2cap_get_peer_mtu_for_local_cid": "0x0000be05", 
    "l2cap_init": "0x0000c1d9", 
    "l2cap_le_send_flow_control_credit": "0x0000c2cf", 
    "l2cap_max_le_mtu": "0x0000c5d9", 
    "l2cap_register_packet_handler": "0x0000c701", 
    "l2cap_register_service": "0x0000c70d", 
    "l2cap_request_can_send_now_event": "0x0000c81d", 
    "l2cap_request_connection_parameter_update": "0x0000c837", 
    "l2cap_send_echo_request": "0x0000cd11", 
    "l2cap_unregister_service": "0x0000cdd1", 
    "le_device_db_add": "0x0000ce29", 
    "le_device_db_find": "0x0000cef1", 
    "le_device_db_from_key": "0x0000cf1d", 
    "le_device_db_iter_cur": "0x0000cf25", 
    "le_device_db_iter_cur_key": "0x0000cf29", 
    "le_device_db_iter_init": "0x0000cf2d", 
    "le_device_db_iter_next": "0x0000cf35", 
    "le_device_db_remove_key": "0x0000cf5b", 
    "ll_aes_encrypt": "0x0000cf89", 
    "ll_config": "0x0000d005", 
    "ll_free": "0x0000d03b", 
    "ll_get_heap_free_size": "0x0000d045", 
    "ll_hint_on_ce_len": "0x0000d059", 
    "ll_legacy_adv_set_interval": "0x0000d091", 
    "ll_malloc": "0x0000d0a1", 
    "ll_query_timing_info": "0x0000d1d9", 
    "ll_register_hci_acl_previewer": "0x0000d225", 
    "ll_scan_set_fixed_channel": "0x0000d289", 
    "ll_set_adv_access_address": "0x0000d4a1", 
    "ll_set_adv_coded_scheme": "0x0000d4ad", 
    "ll_set_conn_acl_report_latency": "0x0000d4d5", 
    "ll_set_conn_coded_scheme": "0x0000d501", 
    "ll_set_conn_latency": "0x0000d529", 
    "ll_set_conn_tx_power": "0x0000d555", 
    "ll_set_def_antenna": "0x0000d599", 
    "ll_set_initiating_coded_scheme": "0x0000d5b5", 
    "ll_set_max_conn_number": "0x0000d5c1", 
    "nibble_for_char": "0x0001e529", 
    "platform_32k_rc_auto_tune": "0x0001e5c9", 
    "platform_32k_rc_tune": "0x0001e645", 
    "platform_calibrate_32k": "0x0001e659", 
    "platform_config": "0x0001e65d", 
    "platform_delete_timer": "0x0001e781", 
    "platform_enable_irq": "0x0001e789", 
    "platform_get_current_task": "0x0001e7c1", 
    "platform_get_gen_os_driver": "0x0001e7e5", 
    "platform_get_heap_status": "0x0001e7ed", 
    "platform_get_link_layer_interf": "0x0001e805", 
    "platform_get_task_handle": "0x0001e80d", 
    "platform_get_timer_counter": "0x0001e82d", 
    "platform_get_us_time": "0x0001e831", 
    "platform_get_version": "0x0001e835", 
    "platform_hrng": "0x0001e83d", 
    "platform_install_isr_stack": "0x0001e845", 
    "platform_install_task_stack": "0x0001e851", 
    "platform_patch_rf_init_data": "0x0001e889", 
    "platform_printf": "0x0001e895", 
    "platform_raise_assertion": "0x0001e8a9", 
    "platform_rand": "0x0001e8bd", 
    "platform_read_info": "0x0001e8c1", 
    "platform_read_persistent_reg": "0x0001e8f1", 
    "platform_reset": "0x0001e901", 
    "platform_set_abs_timer": "0x0001e925", 
    "platform_set_evt_callback": "0x0001e929", 
    "platform_set_evt_callback_table": "0x0001e93d", 
    "platform_set_irq_callback": "0x0001e949", 
    "platform_set_irq_callback_table": "0x0001e965", 
    "platform_set_rf_clk_source": "0x0001e971", 
    "platform_set_rf_init_data": "0x0001e97d", 
    "platform_set_rf_power_mapping": "0x0001e989", 
    "platform_set_timer": "0x0001e995", 
    "platform_shutdown": "0x0001e999", 
    "platform_switch_app": "0x0001e99d", 
    "platform_trace_raw": "0x0001e9c9", 
    "platform_write_persistent_reg": "0x0001e9e1", 
    "printf_hexdump": "0x0001eb95", 
    "pvPortMalloc": "0x0001f681", 
    "pvTaskIncrementMutexHeldCount": "0x0001f769", 
    "pvTimerGetTimerID": "0x0001f781", 
    "pxPortInitialiseStack": "0x0001f7ad", 
    "reverse_128": "0x0001f98d", 
    "reverse_24": "0x0001f993", 
    "reverse_256": "0x0001f999", 
    "reverse_48": "0x0001f99f", 
    "reverse_56": "0x0001f9a5", 
    "reverse_64": "0x0001f9ab", 
    "reverse_bd_addr": "0x0001f9b1", 
    "reverse_bytes": "0x0001f9b7", 
    "sm_add_event_handler": "0x0001fca5", 
    "sm_address_resolution_lookup": "0x0001fdfd", 
    "sm_authenticated": "0x00020179", 
    "sm_authorization_decline": "0x00020187", 
    "sm_authorization_grant": "0x000201a7", 
    "sm_authorization_state": "0x000201c7", 
    "sm_bonding_decline": "0x000201e1", 
    "sm_config": "0x0002063d", 
    "sm_config_conn": "0x00020655", 
    "sm_encryption_key_size": "0x0002080b", 
    "sm_just_works_confirm": "0x00020d91", 
    "sm_le_device_key": "0x000210dd", 
    "sm_passkey_input": "0x00021173", 
    "sm_private_random_address_generation_get": "0x0002152d", 
    "sm_private_random_address_generation_get_mode": "0x00021535", 
    "sm_private_random_address_generation_set_mode": "0x00021541", 
    "sm_private_random_address_generation_set_update_period": "0x00021569", 
    "sm_register_external_ltk_callback": "0x000216a5", 
    "sm_register_oob_data_callback": "0x000216b1", 
    "sm_request_pairing": "0x000216bd", 
    "sm_send_security_request": "0x00022193", 
    "sm_set_accepted_stk_generation_methods": "0x000221b9", 
    "sm_set_authentication_requirements": "0x000221c5", 
    "sm_set_encryption_key_size_range": "0x000221d1", 
    "sscanf_bd_addr": "0x0002252d", 
    "sysSetPublicDeviceAddr": "0x000228e1", 
    "uuid128_to_str": "0x00023069", 
    "uuid_add_bluetooth_prefix": "0x000230c1", 
    "uuid_has_bluetooth_prefix": "0x000230e1", 
    "uxListRemove": "0x000230fd", 
    "uxQueueMessagesWaiting": "0x00023125", 
    "uxQueueMessagesWaitingFromISR": "0x0002314d", 
    "uxQueueSpacesAvailable": "0x00023169", 
    "uxTaskGetStackHighWaterMark": "0x00023195", 
    "uxTaskPriorityGet": "0x000231b5", 
    "uxTaskPriorityGetFromISR": "0x000231d1", 
    "vListInitialise": "0x0002328b", 
    "vListInitialiseItem": "0x000232a1", 
    "vListInsert": "0x000232a7", 
    "vListInsertEnd": "0x000232d7", 
    "vPortEndScheduler": "0x000232f1", 
    "vPortEnterCritical": "0x0002331d", 
    "vPortExitCritical": "0x00023361", 
    "vPortFree": "0x00023395", 
    "vPortSuppressTicksAndSleep": "0x00023429", 
    "vPortValidateInterruptPriority": "0x00023551", 
    "vQueueDelete": "0x000235ad", 
    "vQueueWaitForMessageRestricted": "0x000235d9", 
    "vTaskDelay": "0x00023621", 
    "vTaskInternalSetTimeOutState": "0x0002366d", 
    "vTaskMissedYield": "0x0002367d", 
    "vTaskPlaceOnEventList": "0x00023689", 
    "vTaskPlaceOnEventListRestricted": "0x000236c1", 
    "vTaskPriorityDisinheritAfterTimeout": "0x00023701", 
    "vTaskPrioritySet": "0x000237ad", 
    "vTaskResume": "0x00023875", 
    "vTaskStartScheduler": "0x000238f9", 
    "vTaskStepTick": "0x00023989", 
    "vTaskSuspend": "0x000239b9", 
    "vTaskSuspendAll": "0x00023a75", 
    "vTaskSwitchContext": "0x00023a85", 
    "xPortStartScheduler": "0x00023b29", 
    "xQueueAddToSet": "0x00023bf1", 
    "xQueueCreateCountingSemaphore": "0x00023c15", 
    "xQueueCreateCountingSemaphoreStatic": "0x00023c51", 
    "xQueueCreateMutex": "0x00023c95", 
    "xQueueCreateMutexStatic": "0x00023cab", 
    "xQueueCreateSet": "0x00023cc5", 
    "xQueueGenericCreate": "0x00023ccd", 
    "xQueueGenericCreateStatic": "0x00023d19", 
    "xQueueGenericReset": "0x00023d81", 
    "xQueueGenericSend": "0x00023e0d", 
    "xQueueGenericSendFromISR": "0x00023f79", 
    "xQueueGiveFromISR": "0x00024039", 
    "xQueueGiveMutexRecursive": "0x000240dd", 
    "xQueueIsQueueEmptyFromISR": "0x0002411d", 
    "xQueueIsQueueFullFromISR": "0x00024141", 
    "xQueuePeek": "0x00024169", 
    "xQueuePeekFromISR": "0x00024291", 
    "xQueueReceive": "0x000242fd", 
    "xQueueReceiveFromISR": "0x00024429", 
    "xQueueRemoveFromSet": "0x000244bd", 
    "xQueueSelectFromSet": "0x000244df", 
    "xQueueSelectFromSetFromISR": "0x000244f1", 
    "xQueueSemaphoreTake": "0x00024505", 
    "xQueueTakeMutexRecursive": "0x00024671", 
    "xTaskCheckForTimeOut": "0x000246b5", 
    "xTaskCreate": "0x00024725", 
    "xTaskCreateStatic": "0x00024781", 
    "xTaskGetCurrentTaskHandle": "0x000247f1", 
    "xTaskGetSchedulerState": "0x000247fd", 
    "xTaskGetTickCount": "0x00024819", 
    "xTaskGetTickCountFromISR": "0x00024825", 
    "xTaskIncrementTick": "0x00024835", 
    "xTaskPriorityDisinherit": "0x00024901", 
    "xTaskPriorityInherit": "0x00024995", 
    "xTaskRemoveFromEventList": "0x00024a29", 
    "xTaskResumeAll": "0x00024aa9", 
    "xTaskResumeFromISR": "0x00024b71", 
    "xTimerCreate": "0x00024bfd", 
    "xTimerCreateStatic": "0x00024c31", 
    "xTimerCreateTimerTask": "0x00024c69", 
    "xTimerGenericCommand": "0x00024cd5", 
    "xTimerGetExpiryTime": "0x00024d45", 
    "xTimerGetTimerDaemonTaskHandle": "0x00024d65"
}