{
    "att_dispatch_client_can_send_now": "0x02005245",
    "att_dispatch_client_request_can_send_now_event": "0x0200524b",
    "att_dispatch_register_client": "0x02005251",
    "att_dispatch_register_server": "0x02005265",
    "att_dispatch_server_can_send_now": "0x02005279",
    "att_dispatch_server_request_can_send_now_event": "0x0200527f",
    "att_emit_general_event": "0x02005331",
    "att_server_can_send_packet_now": "0x02005a9d",
    "att_server_deferred_read_response": "0x02005aa1",
    "att_server_get_mtu": "0x02005ae5",
    "att_server_indicate": "0x02005b59",
    "att_server_init": "0x02005bc9",
    "att_server_notify": "0x02005bdb",
    "att_server_register_packet_handler": "0x02005cd9",
    "att_server_request_can_send_now_event": "0x02005d0b",
    "att_set_db": "0x02005d27",
    "att_set_read_callback": "0x02005d39",
    "att_set_write_callback": "0x02005d45",
    "bd_addr_cmp": "0x02005f3f",
    "bd_addr_copy": "0x02005f45",
    "bd_addr_to_str": "0x02005f51",
    "big_endian_read_16": "0x02005f89",
    "big_endian_read_32": "0x02005f91",
    "big_endian_store_16": "0x02005fa5",
    "big_endian_store_32": "0x02005fb1",
    "btstack_config": "0x02006151",
    "btstack_get_capabilities": "0x0200615d",
    "btstack_memory_pool_create": "0x020062bb",
    "btstack_memory_pool_free": "0x020062e5",
    "btstack_memory_pool_get": "0x02006345",
    "btstack_push_user_msg": "0x0200638d",
    "btstack_push_user_runnable": "0x02006399",
    "btstack_reset": "0x020063a5",
    "char_for_nibble": "0x020066bf",
    "gap_add_dev_to_periodic_list": "0x02007135",
    "gap_add_whitelist": "0x02007145",
    "gap_aes_encrypt": "0x02007151",
    "gap_clear_white_lists": "0x02007189",
    "gap_clr_adv_set": "0x02007195",
    "gap_clr_periodic_adv_list": "0x020071a1",
    "gap_connection_parameter_update_negative_reply": "0x020071ad",
    "gap_connection_parameter_update_reply": "0x020071bd",
    "gap_create_connection_cancel": "0x020071e1",
    "gap_default_periodic_adv_sync_transfer_param": "0x020071ed",
    "gap_disconnect": "0x02007205",
    "gap_disconnect2": "0x0200720d",
    "gap_disconnect_all": "0x02007239",
    "gap_ext_create_connection": "0x02007279",
    "gap_get_connection_parameter_range": "0x02007351",
    "gap_le_read_channel_map": "0x02007389",
    "gap_periodic_adv_create_sync": "0x020073e9",
    "gap_periodic_adv_create_sync_cancel": "0x0200740d",
    "gap_periodic_adv_set_info_transfer": "0x02007419",
    "gap_periodic_adv_sync_transfer": "0x02007429",
    "gap_periodic_adv_sync_transfer_param": "0x02007439",
    "gap_periodic_adv_term_sync": "0x02007455",
    "gap_read_antenna_info": "0x020074dd",
    "gap_read_periodic_adv_list_size": "0x020074e9",
    "gap_read_phy": "0x020074f5",
    "gap_read_remote_used_features": "0x02007501",
    "gap_read_remote_version": "0x0200750d",
    "gap_read_rssi": "0x02007519",
    "gap_read_white_lists_size": "0x02007525",
    "gap_remove_whitelist": "0x02007531",
    "gap_rmv_adv_set": "0x020075ad",
    "gap_rmv_dev_from_periodic_list": "0x020075b9",
    "gap_rx_test_v2": "0x020075c9",
    "gap_rx_test_v3": "0x020075d9",
    "gap_set_adv_set_random_addr": "0x02007625",
    "gap_set_callback_for_next_hci": "0x02007649",
    "gap_set_connection_cte_request_enable": "0x02007669",
    "gap_set_connection_cte_response_enable": "0x02007685",
    "gap_set_connection_cte_rx_param": "0x02007695",
    "gap_set_connection_cte_tx_param": "0x020076e9",
    "gap_set_connection_parameter_range": "0x02007735",
    "gap_set_connectionless_cte_tx_enable": "0x0200774d",
    "gap_set_connectionless_cte_tx_param": "0x0200775d",
    "gap_set_connectionless_iq_sampling_enable": "0x020077b9",
    "gap_set_data_length": "0x02007815",
    "gap_set_def_phy": "0x0200782d",
    "gap_set_ext_adv_data": "0x0200783d",
    "gap_set_ext_adv_enable": "0x02007855",
    "gap_set_ext_adv_para": "0x020078c5",
    "gap_set_ext_scan_enable": "0x02007985",
    "gap_set_ext_scan_para": "0x0200799d",
    "gap_set_ext_scan_response_data": "0x02007a3d",
    "gap_set_host_channel_classification": "0x02007a55",
    "gap_set_periodic_adv_data": "0x02007a65",
    "gap_set_periodic_adv_enable": "0x02007ad5",
    "gap_set_periodic_adv_para": "0x02007ae5",
    "gap_set_periodic_adv_rx_enable": "0x02007afd",
    "gap_set_phy": "0x02007b0d",
    "gap_set_random_device_address": "0x02007b29",
    "gap_start_ccm": "0x02007b45",
    "gap_test_end": "0x02007b8d",
    "gap_tx_test_v2": "0x02007b99",
    "gap_tx_test_v4": "0x02007bb1",
    "gap_update_connection_parameters": "0x02007bd5",
    "gap_vendor_tx_continuous_wave": "0x02007c19",
    "gatt_client_cancel_write": "0x020080e5",
    "gatt_client_discover_characteristic_descriptors": "0x02008107",
    "gatt_client_discover_characteristics_for_handle_range_by_uuid128": "0x02008151",
    "gatt_client_discover_characteristics_for_handle_range_by_uuid16": "0x02008195",
    "gatt_client_discover_characteristics_for_service": "0x020081d7",
    "gatt_client_discover_primary_services": "0x02008209",
    "gatt_client_discover_primary_services_by_uuid128": "0x02008237",
    "gatt_client_discover_primary_services_by_uuid16": "0x02008275",
    "gatt_client_exchange_mtu_request": "0x020082af",
    "gatt_client_execute_write": "0x020082dd",
    "gatt_client_find_included_services_for_service": "0x020082ff",
    "gatt_client_get_mtu": "0x02008329",
    "gatt_client_is_ready": "0x020083f5",
    "gatt_client_listen_for_characteristic_value_updates": "0x0200840b",
    "gatt_client_prepare_write": "0x0200842d",
    "gatt_client_read_characteristic_descriptor_using_descriptor_handle": "0x02008465",
    "gatt_client_read_long_characteristic_descriptor_using_descriptor_handle": "0x0200848b",
    "gatt_client_read_long_characteristic_descriptor_using_descriptor_handle_with_offset": "0x02008491",
    "gatt_client_read_long_value_of_characteristic_using_value_handle": "0x020084bb",
    "gatt_client_read_long_value_of_characteristic_using_value_handle_with_offset": "0x020084c1",
    "gatt_client_read_multiple_characteristic_values": "0x020084eb",
    "gatt_client_read_value_of_characteristic_using_value_handle": "0x02008517",
    "gatt_client_read_value_of_characteristics_by_uuid128": "0x02008541",
    "gatt_client_read_value_of_characteristics_by_uuid16": "0x02008581",
    "gatt_client_register_handler": "0x020085bd",
    "gatt_client_reliable_write_long_value_of_characteristic": "0x020085c9",
    "gatt_client_signed_write_without_response": "0x020089f5",
    "gatt_client_write_characteristic_descriptor_using_descriptor_handle": "0x02008b29",
    "gatt_client_write_client_characteristic_configuration": "0x02008b5b",
    "gatt_client_write_long_characteristic_descriptor_using_descriptor_handle": "0x02008bb3",
    "gatt_client_write_long_characteristic_descriptor_using_descriptor_handle_with_offset": "0x02008bc3",
    "gatt_client_write_long_value_of_characteristic": "0x02008bfb",
    "gatt_client_write_long_value_of_characteristic_with_offset": "0x02008c0b",
    "gatt_client_write_value_of_characteristic": "0x02008c43",
    "gatt_client_write_value_of_characteristic_without_response": "0x02008c71",
    "hci_add_event_handler": "0x0200a34d",
    "hci_power_control": "0x0200aafd",
    "hci_register_acl_packet_handler": "0x0200acb1",
    "kv_commit": "0x0200b485",
    "kv_get": "0x0200b4e1",
    "kv_init": "0x0200b4ed",
    "kv_init_backend": "0x0200b509",
    "kv_put": "0x0200b51d",
    "kv_remove": "0x0200b529",
    "kv_remove_all": "0x0200b561",
    "kv_value_modified": "0x0200b591",
    "kv_value_modified_of_key": "0x0200b5ad",
    "kv_visit": "0x0200b5b9",
    "l2cap_add_event_handler": "0x0200b649",
    "l2cap_can_send_packet_now": "0x0200b659",
    "l2cap_create_le_credit_based_connection_request": "0x0200b81d",
    "l2cap_credit_based_send": "0x0200b961",
    "l2cap_credit_based_send_continue": "0x0200b98d",
    "l2cap_disconnect": "0x0200ba09",
    "l2cap_get_le_credit_based_connection_credits": "0x0200bbed",
    "l2cap_get_peer_mtu_for_local_cid": "0x0200bc09",
    "l2cap_init": "0x0200c021",
    "l2cap_le_send_flow_control_credit": "0x0200c1c9",
    "l2cap_max_le_mtu": "0x0200c4c9",
    "l2cap_register_packet_handler": "0x0200c609",
    "l2cap_register_service": "0x0200c615",
    "l2cap_request_can_send_now_event": "0x0200c729",
    "l2cap_request_connection_parameter_update": "0x0200c743",
    "l2cap_send_echo_request": "0x0200cc11",
    "l2cap_unregister_service": "0x0200ccf1",
    "le_device_db_add": "0x0200cd49",
    "le_device_db_find": "0x0200ce11",
    "le_device_db_from_key": "0x0200ce3d",
    "le_device_db_iter_cur": "0x0200ce45",
    "le_device_db_iter_cur_key": "0x0200ce49",
    "le_device_db_iter_init": "0x0200ce4d",
    "le_device_db_iter_next": "0x0200ce55",
    "le_device_db_remove_key": "0x0200ce81",
    "ll_ackable_packet_alloc": "0x0200cead",
    "ll_ackable_packet_get_status": "0x0200cfe9",
    "ll_ackable_packet_run": "0x0200d055",
    "ll_ackable_packet_set_tx_data": "0x0200d10d",
    "ll_adjust_conn_peer_tx_power": "0x0200d129",
    "ll_aes_encrypt": "0x0200d155",
    "ll_allow_nonstandard_adv_type": "0x0200d1d1",
    "ll_attach_cte_to_adv_set": "0x0200d1e9",
    "ll_burst_packet_check_each_rx_pdu": "0x0200d3dd",
    "ll_burst_packet_config_enhanced": "0x0200d439",
    "ll_burst_packet_config_legacy": "0x0200d49d",
    "ll_burst_packet_enable_2m_phy_shorter_ifs": "0x0200d515",
    "ll_burst_packet_flush_tx_fifo": "0x0200d535",
    "ll_burst_packet_initiator_alloc": "0x0200d58d",
    "ll_burst_packet_initiator_get_tx_num": "0x0200d621",
    "ll_burst_packet_initiator_set_param": "0x0200d633",
    "ll_burst_packet_initiator_tx_fifo_push_data": "0x0200d6c5",
    "ll_burst_packet_responder_alloc": "0x0200d735",
    "ll_burst_packet_responder_get_tx_num": "0x0200d81b",
    "ll_burst_packet_responder_set_param": "0x0200d835",
    "ll_burst_packet_responder_tx_fifo_push_data": "0x0200d8e5",
    "ll_burst_packet_run": "0x0200d94d",
    "ll_channel_monitor_alloc": "0x0200da63",
    "ll_channel_monitor_check_each_pdu": "0x0200dae5",
    "ll_channel_monitor_get_1st_pdu_time": "0x0200db51",
    "ll_channel_monitor_run": "0x0200db89",
    "ll_config": "0x0200dc59",
    "ll_conn_abort": "0x0200dc7d",
    "ll_create_conn": "0x0200dcb1",
    "ll_free": "0x0200df2b",
    "ll_get_capabilities": "0x0200df35",
    "ll_get_conn_events_info": "0x0200df55",
    "ll_get_conn_info": "0x0200e03d",
    "ll_get_heap_free_size": "0x0200e08d",
    "ll_get_states": "0x0200e09d",
    "ll_hint_on_ce_len": "0x0200e159",
    "ll_legacy_adv_set_interval": "0x0200e191",
    "ll_lock_frequency": "0x0200e1a1",
    "ll_malloc": "0x0200e205",
    "ll_override_whitening_init_value": "0x0200e20d",
    "ll_raw_packet_alloc": "0x0200e335",
    "ll_raw_packet_free": "0x0200e409",
    "ll_raw_packet_get_bare_rx_data": "0x0200e453",
    "ll_raw_packet_get_iq_samples": "0x0200e513",
    "ll_raw_packet_get_rx_data": "0x0200e5ad",
    "ll_raw_packet_recv": "0x0200e64d",
    "ll_raw_packet_send": "0x0200e721",
    "ll_raw_packet_set_bare_data": "0x0200e83d",
    "ll_raw_packet_set_bare_mode": "0x0200e87b",
    "ll_raw_packet_set_fake_cte_info": "0x0200e97f",
    "ll_raw_packet_set_param": "0x0200e9a1",
    "ll_raw_packet_set_rx_cte": "0x0200ea03",
    "ll_raw_packet_set_tx_cte": "0x0200ea99",
    "ll_raw_packet_set_tx_data": "0x0200ead7",
    "ll_register_hci_acl_previewer": "0x0200eb39",
    "ll_register_hci_conn_pdu_previewer": "0x0200eb4d",
    "ll_scan_set_fixed_channel": "0x0200ebb9",
    "ll_scanner_enable_iq_sampling": "0x0200ebc5",
    "ll_scanner_enable_iq_sampling_on_legacy": "0x0200ec55",
    "ll_set_adv_access_address": "0x0200ef45",
    "ll_set_adv_coded_scheme": "0x0200ef51",
    "ll_set_conn_acl_report_latency": "0x0200efa1",
    "ll_set_conn_coded_scheme": "0x0200efd1",
    "ll_set_conn_interval_unit": "0x0200effd",
    "ll_set_conn_latency": "0x0200f009",
    "ll_set_conn_tx_power": "0x0200f039",
    "ll_set_cte_bit": "0x0200f069",
    "ll_set_def_antenna": "0x0200f091",
    "ll_set_initiating_coded_scheme": "0x0200f0b1",
    "ll_set_max_conn_number": "0x0200f0bd",
    "ll_set_tx_power_range": "0x0200f165",
    "ll_unlock_frequency": "0x0200f18d",
    "nibble_for_char": "0x020246c5",
    "platform_calibrate_rt_clk": "0x02024751",
    "platform_call_on_stack": "0x0200306d",
    "platform_cancel_us_timer": "0x02024755",
    "platform_config": "0x02024759",
    "platform_controller_run": "0x020248a1",
    "platform_create_us_timer": "0x020248d5",
    "platform_create_us_timer2": "0x020248e3",
    "platform_delete_timer": "0x020248ef",
    "platform_enable_irq": "0x020248f5",
    "platform_get_gen_os_driver": "0x02024929",
    "platform_get_link_layer_interf": "0x02024935",
    "platform_get_task_handle": "0x0202493d",
    "platform_get_timer_counter": "0x02024955",
    "platform_get_us_time": "0x02024959",
    "platform_get_version": "0x0202495d",
    "platform_hrng": "0x02024979",
    "platform_init_controller": "0x02024981",
    "platform_os_idle_resumed_hook": "0x0202499d",
    "platform_patch_rf_init_data": "0x020249a1",
    "platform_post_sleep_processing": "0x020249ad",
    "platform_pre_sleep_processing": "0x020249b3",
    "platform_pre_suppress_cycles_and_sleep_processing": "0x020249b9",
    "platform_pre_suppress_ticks_and_sleep_processing": "0x020249bd",
    "platform_printf": "0x020249c9",
    "platform_raise_assertion": "0x020249dd",
    "platform_rand": "0x020249f1",
    "platform_read_info": "0x020249f5",
    "platform_read_persistent_reg": "0x02024a25",
    "platform_reset": "0x02024a45",
    "platform_rt_rc_auto_tune": "0x02024a79",
    "platform_rt_rc_auto_tune2": "0x02024a81",
    "platform_rt_rc_tune": "0x02024ae5",
    "platform_set_abs_timer": "0x02024b0d",
    "platform_set_evt_callback": "0x02024b11",
    "platform_set_evt_callback_table": "0x02024b25",
    "platform_set_irq_callback": "0x02024b31",
    "platform_set_irq_callback_table": "0x02024b4d",
    "platform_set_rf_clk_source": "0x02024b59",
    "platform_set_rf_init_data": "0x02024b65",
    "platform_set_rf_power_mapping": "0x02024b71",
    "platform_set_timer": "0x02024b7d",
    "platform_shutdown": "0x02024b81",
    "platform_switch_app": "0x02024b85",
    "platform_trace_raw": "0x02024ba5",
    "platform_write_persistent_reg": "0x02024bbd",
    "printf_hexdump": "0x02024be1",
    "reverse_128": "0x02024fa5",
    "reverse_24": "0x02024fab",
    "reverse_256": "0x02024fb1",
    "reverse_48": "0x02024fb7",
    "reverse_56": "0x02024fbd",
    "reverse_64": "0x02024fc3",
    "reverse_bd_addr": "0x02024fc9",
    "reverse_bytes": "0x02024fcf",
    "sm_add_event_handler": "0x02025379",
    "sm_address_resolution_lookup": "0x020254d1",
    "sm_authenticated": "0x02025889",
    "sm_authorization_decline": "0x02025897",
    "sm_authorization_grant": "0x020258b7",
    "sm_authorization_state": "0x020258d7",
    "sm_bonding_decline": "0x020258f1",
    "sm_config": "0x02025d45",
    "sm_config_conn": "0x02025d81",
    "sm_encryption_key_size": "0x02025f3b",
    "sm_just_works_confirm": "0x020264f1",
    "sm_le_device_key": "0x02026845",
    "sm_passkey_input": "0x020268db",
    "sm_private_random_address_generation_get": "0x02026ca5",
    "sm_private_random_address_generation_get_mode": "0x02026cad",
    "sm_private_random_address_generation_set_mode": "0x02026cb9",
    "sm_private_random_address_generation_set_update_period": "0x02026ce1",
    "sm_register_external_ltk_callback": "0x02026e1d",
    "sm_register_oob_data_callback": "0x02026e29",
    "sm_request_pairing": "0x02026e35",
    "sm_send_security_request": "0x0202792f",
    "sm_set_accepted_stk_generation_methods": "0x02027955",
    "sm_set_authentication_requirements": "0x02027961",
    "sm_set_encryption_key_size_range": "0x02027971",
    "sm_set_key_distribution_flags": "0x0202797d",
    "sm_set_persistent_irk": "0x02027989",
    "sscanf_bd_addr": "0x02027d55",
    "sysSetPublicDeviceAddr": "0x020285f9",
    "uuid128_to_str": "0x02028fa5",
    "uuid_add_bluetooth_prefix": "0x02028ffd",
    "uuid_has_bluetooth_prefix": "0x0202901d"
}