{
    "att_dispatch_client_can_send_now": "0x0200513d",
    "att_dispatch_client_request_can_send_now_event": "0x02005143",
    "att_dispatch_register_client": "0x02005149",
    "att_dispatch_register_server": "0x0200515d",
    "att_dispatch_server_can_send_now": "0x02005171",
    "att_dispatch_server_request_can_send_now_event": "0x02005177",
    "att_emit_general_event": "0x02005229",
    "att_server_can_send_packet_now": "0x02005995",
    "att_server_deferred_read_response": "0x02005999",
    "att_server_get_mtu": "0x020059b1",
    "att_server_indicate": "0x02005a25",
    "att_server_init": "0x02005aa9",
    "att_server_notify": "0x02005ae5",
    "att_server_register_packet_handler": "0x02005bfd",
    "att_server_request_can_send_now_event": "0x02005c2f",
    "att_set_db": "0x02005c4b",
    "att_set_read_callback": "0x02005c5d",
    "att_set_write_callback": "0x02005c69",
    "bd_addr_cmp": "0x02005e63",
    "bd_addr_copy": "0x02005e69",
    "bd_addr_to_str": "0x02005e75",
    "big_endian_read_16": "0x02005ead",
    "big_endian_read_32": "0x02005eb5",
    "big_endian_store_16": "0x02005ec9",
    "big_endian_store_32": "0x02005ed5",
    "btstack_config": "0x02006045",
    "btstack_get_capabilities": "0x02006051",
    "btstack_memory_pool_create": "0x020061af",
    "btstack_memory_pool_free": "0x020061d9",
    "btstack_memory_pool_get": "0x02006239",
    "btstack_push_user_msg": "0x02006281",
    "btstack_push_user_runnable": "0x0200628d",
    "btstack_reset": "0x02006299",
    "char_for_nibble": "0x020065b3",
    "eTaskConfirmSleepModeStatus": "0x020069b5",
    "gap_add_dev_to_periodic_list": "0x02007089",
    "gap_add_dev_to_resolving_list": "0x02007099",
    "gap_add_whitelist": "0x020070cd",
    "gap_aes_encrypt": "0x020070d9",
    "gap_clear_resolving_list": "0x02007111",
    "gap_clear_white_lists": "0x0200711d",
    "gap_clr_adv_set": "0x02007129",
    "gap_clr_periodic_adv_list": "0x02007135",
    "gap_connection_parameter_update_negative_reply": "0x02007141",
    "gap_connection_parameter_update_reply": "0x02007151",
    "gap_create_connection_cancel": "0x02007175",
    "gap_default_periodic_adv_sync_transfer_param": "0x02007181",
    "gap_disconnect": "0x02007199",
    "gap_disconnect2": "0x020071a1",
    "gap_disconnect_all": "0x020071cd",
    "gap_ext_create_connection": "0x0200720d",
    "gap_ext_create_connection_v2": "0x020072b9",
    "gap_get_connection_parameter_range": "0x020073b9",
    "gap_le_read_channel_map": "0x020073f1",
    "gap_periodic_adv_create_sync": "0x02007451",
    "gap_periodic_adv_create_sync_cancel": "0x02007475",
    "gap_periodic_adv_set_info_transfer": "0x02007481",
    "gap_periodic_adv_sync_transfer": "0x02007491",
    "gap_periodic_adv_sync_transfer_param": "0x020074a1",
    "gap_periodic_adv_term_sync": "0x020074bd",
    "gap_read_antenna_info": "0x02007545",
    "gap_read_local_resolving_addr": "0x0200755d",
    "gap_read_local_tx_power_level": "0x02007569",
    "gap_read_peer_resolving_addr": "0x02007579",
    "gap_read_periodic_adv_list_size": "0x02007585",
    "gap_read_phy": "0x02007591",
    "gap_read_remote_tx_power_level": "0x0200759d",
    "gap_read_remote_used_features": "0x020075ad",
    "gap_read_remote_version": "0x020075b9",
    "gap_read_rssi": "0x020075c5",
    "gap_read_white_lists_size": "0x020075d1",
    "gap_remove_dev_from_resolving_list": "0x020075dd",
    "gap_remove_whitelist": "0x020075e9",
    "gap_rmv_adv_set": "0x02007665",
    "gap_rmv_dev_from_periodic_list": "0x02007671",
    "gap_rx_test_v2": "0x02007681",
    "gap_rx_test_v3": "0x02007691",
    "gap_set_addr_resolution_enable": "0x020076dd",
    "gap_set_adv_set_random_addr": "0x020076e9",
    "gap_set_callback_for_next_hci": "0x0200770d",
    "gap_set_connection_cte_request_enable": "0x0200772d",
    "gap_set_connection_cte_response_enable": "0x02007749",
    "gap_set_connection_cte_rx_param": "0x02007759",
    "gap_set_connection_cte_tx_param": "0x020077ad",
    "gap_set_connection_parameter_range": "0x020077f9",
    "gap_set_connectionless_cte_tx_enable": "0x02007811",
    "gap_set_connectionless_cte_tx_param": "0x02007821",
    "gap_set_connectionless_iq_sampling_enable": "0x0200787d",
    "gap_set_data_length": "0x020078d9",
    "gap_set_def_phy": "0x020078f1",
    "gap_set_default_subrate": "0x02007901",
    "gap_set_ext_adv_data": "0x0200791d",
    "gap_set_ext_adv_enable": "0x02007935",
    "gap_set_ext_adv_para": "0x020079a5",
    "gap_set_ext_scan_enable": "0x02007a65",
    "gap_set_ext_scan_para": "0x02007a7d",
    "gap_set_ext_scan_response_data": "0x02007b1d",
    "gap_set_host_channel_classification": "0x02007b35",
    "gap_set_path_loss_reporting_enable": "0x02007b45",
    "gap_set_path_loss_reporting_param": "0x02007b55",
    "gap_set_periodic_adv_data": "0x02007b71",
    "gap_set_periodic_adv_enable": "0x02007be1",
    "gap_set_periodic_adv_para": "0x02007bf1",
    "gap_set_periodic_adv_para_v2": "0x02007c09",
    "gap_set_periodic_adv_rsp_data": "0x02007c2d",
    "gap_set_periodic_adv_rx_enable": "0x02007c51",
    "gap_set_periodic_adv_subevent_data": "0x02007c61",
    "gap_set_periodic_sync_subevent": "0x02007cf9",
    "gap_set_phy": "0x02007d11",
    "gap_set_privacy_mode": "0x02007d2d",
    "gap_set_random_device_address": "0x02007d3d",
    "gap_set_resolvable_private_addr_timeout": "0x02007d49",
    "gap_set_tx_power_reporting_enable": "0x02007d55",
    "gap_start_ccm": "0x02007d75",
    "gap_subrate_request": "0x02007dbd",
    "gap_test_end": "0x02007dd9",
    "gap_tx_test_v2": "0x02007de5",
    "gap_tx_test_v4": "0x02007dfd",
    "gap_update_connection_parameters": "0x02007e21",
    "gap_vendor_tx_continuous_wave": "0x02007e65",
    "gatt_client_cancel_write": "0x02008331",
    "gatt_client_discover_characteristic_descriptors": "0x02008353",
    "gatt_client_discover_characteristics_for_handle_range_by_uuid128": "0x0200839d",
    "gatt_client_discover_characteristics_for_handle_range_by_uuid16": "0x020083e1",
    "gatt_client_discover_characteristics_for_service": "0x02008423",
    "gatt_client_discover_primary_services": "0x02008455",
    "gatt_client_discover_primary_services_by_uuid128": "0x02008483",
    "gatt_client_discover_primary_services_by_uuid16": "0x020084c1",
    "gatt_client_exchange_mtu_request": "0x020084fb",
    "gatt_client_execute_write": "0x02008529",
    "gatt_client_find_included_services_for_service": "0x0200854b",
    "gatt_client_get_mtu": "0x02008575",
    "gatt_client_is_ready": "0x02008641",
    "gatt_client_listen_for_characteristic_value_updates": "0x02008657",
    "gatt_client_prepare_write": "0x02008679",
    "gatt_client_read_characteristic_descriptor_using_descriptor_handle": "0x020086b1",
    "gatt_client_read_long_characteristic_descriptor_using_descriptor_handle": "0x020086d7",
    "gatt_client_read_long_characteristic_descriptor_using_descriptor_handle_with_offset": "0x020086dd",
    "gatt_client_read_long_value_of_characteristic_using_value_handle": "0x02008707",
    "gatt_client_read_long_value_of_characteristic_using_value_handle_with_offset": "0x0200870d",
    "gatt_client_read_multiple_characteristic_values": "0x02008737",
    "gatt_client_read_value_of_characteristic_using_value_handle": "0x02008763",
    "gatt_client_read_value_of_characteristics_by_uuid128": "0x0200878d",
    "gatt_client_read_value_of_characteristics_by_uuid16": "0x020087cd",
    "gatt_client_register_handler": "0x02008809",
    "gatt_client_reliable_write_long_value_of_characteristic": "0x02008815",
    "gatt_client_signed_write_without_response": "0x02008c41",
    "gatt_client_write_characteristic_descriptor_using_descriptor_handle": "0x02008d75",
    "gatt_client_write_client_characteristic_configuration": "0x02008da7",
    "gatt_client_write_long_characteristic_descriptor_using_descriptor_handle": "0x02008dff",
    "gatt_client_write_long_characteristic_descriptor_using_descriptor_handle_with_offset": "0x02008e0f",
    "gatt_client_write_long_value_of_characteristic": "0x02008e47",
    "gatt_client_write_long_value_of_characteristic_with_offset": "0x02008e57",
    "gatt_client_write_value_of_characteristic": "0x02008e8f",
    "gatt_client_write_value_of_characteristic_without_response": "0x02008ebd",
    "hci_add_event_handler": "0x0200a5a5",
    "hci_power_control": "0x0200ad55",
    "hci_register_acl_packet_handler": "0x0200af09",
    "kv_commit": "0x0200b6e5",
    "kv_get": "0x0200b741",
    "kv_init": "0x0200b74d",
    "kv_init_backend": "0x0200b769",
    "kv_put": "0x0200b77d",
    "kv_remove": "0x0200b789",
    "kv_remove_all": "0x0200b7c1",
    "kv_value_modified": "0x0200b7f1",
    "kv_value_modified_of_key": "0x0200b80d",
    "kv_visit": "0x0200b819",
    "l2cap_add_event_handler": "0x0200b8a9",
    "l2cap_can_send_packet_now": "0x0200b8b9",
    "l2cap_create_le_credit_based_connection_request": "0x0200ba7d",
    "l2cap_credit_based_send": "0x0200bbc1",
    "l2cap_credit_based_send_continue": "0x0200bbed",
    "l2cap_disconnect": "0x0200bc69",
    "l2cap_get_le_credit_based_connection_credits": "0x0200be4d",
    "l2cap_get_peer_mtu_for_local_cid": "0x0200be69",
    "l2cap_init": "0x0200c281",
    "l2cap_le_send_flow_control_credit": "0x0200c429",
    "l2cap_max_le_mtu": "0x0200c729",
    "l2cap_register_packet_handler": "0x0200c851",
    "l2cap_register_service": "0x0200c85d",
    "l2cap_request_can_send_now_event": "0x0200c971",
    "l2cap_request_connection_parameter_update": "0x0200c98b",
    "l2cap_send_echo_request": "0x0200ce59",
    "l2cap_unregister_service": "0x0200cf39",
    "le_device_db_add": "0x0200cf91",
    "le_device_db_find": "0x0200d059",
    "le_device_db_from_key": "0x0200d085",
    "le_device_db_iter_cur": "0x0200d08d",
    "le_device_db_iter_cur_key": "0x0200d091",
    "le_device_db_iter_init": "0x0200d095",
    "le_device_db_iter_next": "0x0200d09d",
    "le_device_db_remove_key": "0x0200d0c9",
    "ll_ackable_packet_alloc": "0x0200d0f5",
    "ll_ackable_packet_get_status": "0x0200d231",
    "ll_ackable_packet_run": "0x0200d29d",
    "ll_ackable_packet_set_tx_data": "0x0200d355",
    "ll_adjust_conn_peer_tx_power": "0x0200d371",
    "ll_aes_encrypt": "0x0200d39d",
    "ll_allow_nonstandard_adv_type": "0x0200d419",
    "ll_attach_cte_to_adv_set": "0x0200d431",
    "ll_burst_packet_check_each_rx_pdu": "0x0200d625",
    "ll_burst_packet_config_enhanced": "0x0200d681",
    "ll_burst_packet_config_legacy": "0x0200d6e5",
    "ll_burst_packet_enable_2m_phy_shorter_ifs": "0x0200d75d",
    "ll_burst_packet_flush_tx_fifo": "0x0200d77d",
    "ll_burst_packet_initiator_alloc": "0x0200d7d5",
    "ll_burst_packet_initiator_get_tx_num": "0x0200d869",
    "ll_burst_packet_initiator_set_param": "0x0200d87b",
    "ll_burst_packet_initiator_tx_fifo_push_data": "0x0200d90d",
    "ll_burst_packet_responder_alloc": "0x0200d97d",
    "ll_burst_packet_responder_get_tx_num": "0x0200da63",
    "ll_burst_packet_responder_set_param": "0x0200da7d",
    "ll_burst_packet_responder_tx_fifo_push_data": "0x0200db2d",
    "ll_burst_packet_run": "0x0200db95",
    "ll_channel_monitor_alloc": "0x0200dcab",
    "ll_channel_monitor_check_each_pdu": "0x0200dd2d",
    "ll_channel_monitor_get_1st_pdu_time": "0x0200dd99",
    "ll_channel_monitor_run": "0x0200ddd1",
    "ll_config": "0x0200dea1",
    "ll_conn_abort": "0x0200dec5",
    "ll_create_conn": "0x0200def9",
    "ll_dhkey_generated": "0x0200e175",
    "ll_free": "0x0200e1a9",
    "ll_get_capabilities": "0x0200e1b5",
    "ll_get_conn_events_info": "0x0200e1d5",
    "ll_get_conn_info": "0x0200e2bd",
    "ll_get_heap_free_size": "0x0200e30d",
    "ll_get_states": "0x0200e31d",
    "ll_hint_on_ce_len": "0x0200e3d9",
    "ll_install_ecc_engine": "0x0200e411",
    "ll_legacy_adv_set_interval": "0x0200e41d",
    "ll_lock_frequency": "0x0200e42d",
    "ll_malloc": "0x0200e491",
    "ll_override_whitening_init_value": "0x0200e499",
    "ll_p256_key_pair_generated": "0x0200e4b1",
    "ll_raw_packet_alloc": "0x0200e5f5",
    "ll_raw_packet_free": "0x0200e6c9",
    "ll_raw_packet_get_bare_rx_data": "0x0200e713",
    "ll_raw_packet_get_iq_samples": "0x0200e7d3",
    "ll_raw_packet_get_rx_data": "0x0200e86d",
    "ll_raw_packet_recv": "0x0200e90d",
    "ll_raw_packet_send": "0x0200e9e1",
    "ll_raw_packet_set_bare_data": "0x0200eafd",
    "ll_raw_packet_set_bare_mode": "0x0200eb3b",
    "ll_raw_packet_set_fake_cte_info": "0x0200ec3f",
    "ll_raw_packet_set_param": "0x0200ec61",
    "ll_raw_packet_set_rx_cte": "0x0200ecc3",
    "ll_raw_packet_set_tx_cte": "0x0200ed59",
    "ll_raw_packet_set_tx_data": "0x0200ed97",
    "ll_register_hci_acl_previewer": "0x0200edf9",
    "ll_register_hci_conn_pdu_previewer": "0x0200ee0d",
    "ll_scan_set_fixed_channel": "0x0200ee79",
    "ll_scanner_enable_iq_sampling": "0x0200ee85",
    "ll_scanner_enable_iq_sampling_on_legacy": "0x0200ef15",
    "ll_set_adv_access_address": "0x0200f205",
    "ll_set_adv_coded_scheme": "0x0200f211",
    "ll_set_conn_acl_report_latency": "0x0200f249",
    "ll_set_conn_coded_scheme": "0x0200f279",
    "ll_set_conn_interval_unit": "0x0200f2a5",
    "ll_set_conn_latency": "0x0200f2b1",
    "ll_set_conn_tx_power": "0x0200f2e1",
    "ll_set_cte_bit": "0x0200f311",
    "ll_set_def_antenna": "0x0200f339",
    "ll_set_initiating_coded_scheme": "0x0200f359",
    "ll_set_max_conn_number": "0x0200f365",
    "ll_set_tx_power_range": "0x0200f40d",
    "ll_unlock_frequency": "0x0200f435",
    "nibble_for_char": "0x02024829",
    "platform_calibrate_rt_clk": "0x020248c7",
    "platform_call_on_stack": "0x0200311d",
    "platform_cancel_us_timer": "0x020248cb",
    "platform_config": "0x020248d1",
    "platform_controller_run": "0x02024a01",
    "platform_create_us_timer": "0x02024a35",
    "platform_create_us_timer2": "0x02024a43",
    "platform_delete_timer": "0x02024a4f",
    "platform_enable_irq": "0x02024a55",
    "platform_get_current_task": "0x02024a89",
    "platform_get_gen_os_driver": "0x02024ab9",
    "platform_get_heap_status": "0x02024acd",
    "platform_get_link_layer_interf": "0x02024ae5",
    "platform_get_rtos_heap_mem": "0x02024aed",
    "platform_get_task_handle": "0x02024afd",
    "platform_get_timer_counter": "0x02024b2d",
    "platform_get_us_time": "0x02024b31",
    "platform_get_version": "0x02024b35",
    "platform_hrng": "0x02024b51",
    "platform_init_controller": "0x02024b59",
    "platform_install_isr_stack": "0x02024b75",
    "platform_install_task_stack": "0x02024b81",
    "platform_os_idle_resumed_hook": "0x02024ba1",
    "platform_patch_rf_init_data": "0x02024ba5",
    "platform_post_sleep_processing": "0x02024bb1",
    "platform_pre_sleep_processing": "0x02024bb7",
    "platform_pre_suppress_cycles_and_sleep_processing": "0x02024bbd",
    "platform_pre_suppress_ticks_and_sleep_processing": "0x02024bc1",
    "platform_printf": "0x02024bcd",
    "platform_raise_assertion": "0x02024be1",
    "platform_rand": "0x02024bf5",
    "platform_read_info": "0x02024bf9",
    "platform_read_persistent_reg": "0x02024c29",
    "platform_reset": "0x02024c49",
    "platform_rt_rc_auto_tune": "0x02024c99",
    "platform_rt_rc_auto_tune2": "0x02024ca1",
    "platform_rt_rc_tune": "0x02024d01",
    "platform_set_abs_timer": "0x02024d29",
    "platform_set_evt_callback": "0x02024d2d",
    "platform_set_evt_callback_table": "0x02024d41",
    "platform_set_irq_callback": "0x02024d4d",
    "platform_set_irq_callback_table": "0x02024d69",
    "platform_set_rf_clk_source": "0x02024d75",
    "platform_set_rf_init_data": "0x02024d81",
    "platform_set_rf_power_mapping": "0x02024d8d",
    "platform_set_timer": "0x02024d99",
    "platform_shutdown": "0x02024d9d",
    "platform_switch_app": "0x02024da1",
    "platform_trace_raw": "0x02024dbd",
    "platform_write_persistent_reg": "0x02024dd5",
    "printf_hexdump": "0x02024fcd",
    "pvPortMalloc": "0x02025a71",
    "pvTaskIncrementMutexHeldCount": "0x02025b59",
    "pvTimerGetTimerID": "0x02025b71",
    "pxPortInitialiseStack": "0x02025b9d",
    "reverse_128": "0x02025df5",
    "reverse_24": "0x02025dfb",
    "reverse_256": "0x02025e01",
    "reverse_48": "0x02025e07",
    "reverse_56": "0x02025e0d",
    "reverse_64": "0x02025e13",
    "reverse_bd_addr": "0x02025e19",
    "reverse_bytes": "0x02025e1f",
    "sm_add_event_handler": "0x020261d9",
    "sm_address_resolution_lookup": "0x02026301",
    "sm_authenticated": "0x02026759",
    "sm_authorization_decline": "0x02026767",
    "sm_authorization_grant": "0x02026787",
    "sm_authorization_state": "0x020267a7",
    "sm_bonding_decline": "0x020267c1",
    "sm_config": "0x02026c41",
    "sm_config_conn": "0x02026c7d",
    "sm_encryption_key_size": "0x02026e63",
    "sm_just_works_confirm": "0x02027acd",
    "sm_le_device_key": "0x02027eb1",
    "sm_numeric_comparison_confirm": "0x02028025",
    "sm_passkey_input": "0x02028063",
    "sm_private_random_address_generation_get": "0x02028659",
    "sm_private_random_address_generation_get_mode": "0x02028661",
    "sm_private_random_address_generation_set_mode": "0x0202866d",
    "sm_private_random_address_generation_set_update_period": "0x02028695",
    "sm_register_external_ltk_callback": "0x02028929",
    "sm_register_oob_data_callback": "0x02028935",
    "sm_register_sc_oob_data_callback": "0x02028941",
    "sm_request_pairing": "0x0202894d",
    "sm_sc_generate_oob_data": "0x020295f1",
    "sm_send_security_request": "0x02029911",
    "sm_set_accepted_stk_generation_methods": "0x02029939",
    "sm_set_authentication_requirements": "0x02029945",
    "sm_set_encryption_key_size_range": "0x02029955",
    "sm_set_key_distribution_flags": "0x02029961",
    "sm_set_persistent_irk": "0x0202996d",
    "sscanf_bd_addr": "0x02029d85",
    "sysSetPublicDeviceAddr": "0x0202a58d",
    "uuid128_to_str": "0x0202af11",
    "uuid_add_bluetooth_prefix": "0x0202af69",
    "uuid_has_bluetooth_prefix": "0x0202af89",
    "uxListRemove": "0x0202afa5",
    "uxQueueMessagesWaiting": "0x0202afcd",
    "uxQueueMessagesWaitingFromISR": "0x0202aff5",
    "uxQueueSpacesAvailable": "0x0202b011",
    "uxTaskGetStackHighWaterMark": "0x0202b03d",
    "uxTaskPriorityGet": "0x0202b05d",
    "uxTaskPriorityGetFromISR": "0x0202b079",
    "vListInitialise": "0x0202b157",
    "vListInitialiseItem": "0x0202b16d",
    "vListInsert": "0x0202b173",
    "vListInsertEnd": "0x0202b1a3",
    "vPortEndScheduler": "0x0202b1bd",
    "vPortEnterCritical": "0x0202b1e9",
    "vPortExitCritical": "0x0202b22d",
    "vPortFree": "0x0202b261",
    "vPortSuppressTicksAndSleep": "0x0202b305",
    "vPortValidateInterruptPriority": "0x0202b425",
    "vQueueDelete": "0x0202b481",
    "vQueueWaitForMessageRestricted": "0x0202b4ad",
    "vTaskDelay": "0x0202b4f1",
    "vTaskInternalSetTimeOutState": "0x0202b53d",
    "vTaskMissedYield": "0x0202b54d",
    "vTaskPlaceOnEventList": "0x0202b559",
    "vTaskPlaceOnEventListRestricted": "0x0202b591",
    "vTaskPriorityDisinheritAfterTimeout": "0x0202b5d1",
    "vTaskPrioritySet": "0x0202b67d",
    "vTaskResume": "0x0202b745",
    "vTaskStartScheduler": "0x0202b7c9",
    "vTaskStepTick": "0x0202b859",
    "vTaskSuspend": "0x0202b889",
    "vTaskSuspendAll": "0x0202b945",
    "vTaskSwitchContext": "0x0202b955",
    "xPortStartScheduler": "0x0202b9e9",
    "xQueueAddToSet": "0x0202baad",
    "xQueueCreateCountingSemaphore": "0x0202bad1",
    "xQueueCreateCountingSemaphoreStatic": "0x0202bb0d",
    "xQueueCreateMutex": "0x0202bb51",
    "xQueueCreateMutexStatic": "0x0202bb67",
    "xQueueCreateSet": "0x0202bb81",
    "xQueueGenericCreate": "0x0202bb89",
    "xQueueGenericCreateStatic": "0x0202bbd5",
    "xQueueGenericReset": "0x0202bc3d",
    "xQueueGenericSend": "0x0202bcc9",
    "xQueueGenericSendFromISR": "0x0202be35",
    "xQueueGiveFromISR": "0x0202bef5",
    "xQueueGiveMutexRecursive": "0x0202bf99",
    "xQueueIsQueueEmptyFromISR": "0x0202bfd9",
    "xQueueIsQueueFullFromISR": "0x0202bffd",
    "xQueuePeek": "0x0202c025",
    "xQueuePeekFromISR": "0x0202c14d",
    "xQueueReceive": "0x0202c1b9",
    "xQueueReceiveFromISR": "0x0202c2e5",
    "xQueueRemoveFromSet": "0x0202c379",
    "xQueueSelectFromSet": "0x0202c39b",
    "xQueueSelectFromSetFromISR": "0x0202c3ad",
    "xQueueSemaphoreTake": "0x0202c3c1",
    "xQueueTakeMutexRecursive": "0x0202c52d",
    "xTaskCheckForTimeOut": "0x0202c571",
    "xTaskCreate": "0x0202c5e1",
    "xTaskCreateStatic": "0x0202c63d",
    "xTaskGetCurrentTaskHandle": "0x0202c6ad",
    "xTaskGetSchedulerState": "0x0202c6b9",
    "xTaskGetTickCount": "0x0202c6d5",
    "xTaskGetTickCountFromISR": "0x0202c6e1",
    "xTaskIncrementTick": "0x0202c6f1",
    "xTaskPriorityDisinherit": "0x0202c7bd",
    "xTaskPriorityInherit": "0x0202c851",
    "xTaskRemoveFromEventList": "0x0202c8e5",
    "xTaskResumeAll": "0x0202c965",
    "xTaskResumeFromISR": "0x0202ca2d",
    "xTimerCreate": "0x0202cab9",
    "xTimerCreateStatic": "0x0202caed",
    "xTimerCreateTimerTask": "0x0202cb25",
    "xTimerGenericCommand": "0x0202cb91",
    "xTimerGetExpiryTime": "0x0202cc01",
    "xTimerGetTimerDaemonTaskHandle": "0x0202cc21"
}